hintbot/__init__.py
hintbot/_version.py
hintbot/application.py
hintbot/handlers.py
hintbot/labextension/package.json
hintbot/labextension/schemas/hintbot/package.json.orig
hintbot/labextension/schemas/hintbot/plugin.json
hintbot/labextension/static/262.e5e806284b7ed86cafe0.js
hintbot/labextension/static/728.c2de729da0efe3d33291.js
hintbot/labextension/static/972.b225bf2c0c7013dce887.js
hintbot/labextension/static/remoteEntry.77bd08ff349e90e651b6.js
hintbot/labextension/static/style.js
hintbot/labextension/static/third-party-licenses.json
screenshots/student_frontend_jx_consent.png
screenshots/student_frontend_jx_environment.png
screenshots/student_frontend_jx_escalation.png
screenshots/student_frontend_jx_feedback.png
screenshots/student_frontend_jx_hint.png
screenshots/student_frontend_jx_hint_description.png
screenshots/student_frontend_jx_reflection.png
jx_loop_hint-0.0.3.data/data/etc/jupyter/jupyter_server_config.d/hintbot.json
jx_loop_hint-0.0.3.data/data/share/jupyter/labextensions/hintbot/package.json
jx_loop_hint-0.0.3.data/data/share/jupyter/labextensions/hintbot/schemas/hintbot/package.json.orig
jx_loop_hint-0.0.3.data/data/share/jupyter/labextensions/hintbot/schemas/hintbot/plugin.json
jx_loop_hint-0.0.3.data/data/share/jupyter/labextensions/hintbot/static/262.e5e806284b7ed86cafe0.js
jx_loop_hint-0.0.3.data/data/share/jupyter/labextensions/hintbot/static/728.c2de729da0efe3d33291.js
jx_loop_hint-0.0.3.data/data/share/jupyter/labextensions/hintbot/static/972.b225bf2c0c7013dce887.js
jx_loop_hint-0.0.3.data/data/share/jupyter/labextensions/hintbot/static/remoteEntry.77bd08ff349e90e651b6.js
jx_loop_hint-0.0.3.data/data/share/jupyter/labextensions/hintbot/static/style.js
jx_loop_hint-0.0.3.data/data/share/jupyter/labextensions/hintbot/static/third-party-licenses.json
jx_loop_hint-0.0.3.data/data/share/jupyter/labextensions/hintbot/install.json
jx_loop_hint-0.0.3.dist-info/METADATA
jx_loop_hint-0.0.3.dist-info/WHEEL
jx_loop_hint-0.0.3.dist-info/licenses/LICENSE
jx_loop_hint-0.0.3.dist-info/RECORD
