Metadata-Version: 2.4
Name: jx-loop-hint
Version: 0.0.3
Dynamic: Keywords
Summary: A JupyterLab extension.
Project-URL: Homepage, https://github.com/machine-teaching-group/sigcse2026-closing-the-loop/frontend_student_jx
Project-URL: Bug Tracker, https://github.com/machine-teaching-group/sigcse2026-closing-the-loop/frontend_student_jx/issues
Project-URL: Repository, https://github.com/educational-technology-collective/hintbot.git
Author-email: etc <mphung@mpi-sws.org>
License: BSD 3-Clause License
License-File: LICENSE
Classifier: Framework :: Jupyter
Classifier: Framework :: Jupyter :: JupyterLab
Classifier: Framework :: Jupyter :: JupyterLab :: 4
Classifier: Framework :: Jupyter :: JupyterLab :: Extensions
Classifier: Framework :: Jupyter :: JupyterLab :: Extensions :: Prebuilt
Classifier: License :: OSI Approved :: BSD License
Classifier: Programming Language :: Python
Classifier: Programming Language :: Python :: 3
Classifier: Programming Language :: Python :: 3.8
Classifier: Programming Language :: Python :: 3.9
Classifier: Programming Language :: Python :: 3.10
Classifier: Programming Language :: Python :: 3.11
Classifier: Programming Language :: Python :: 3.12
Classifier: Programming Language :: Python :: 3.13
Classifier: Programming Language :: Python :: 3.14
Requires-Python: >=3.8
Requires-Dist: jupyter-server<3,>=2.0.1
Requires-Dist: jupyterlab-pioneer>=1.6.0
Requires-Dist: jupyterlab<5,>=4.1.0
Requires-Dist: requests>=2.28
